tensorbank/__init__.py
tensorbank/tf/__init__.py
tensorbank/tf/axis_aligned_boxes.py
tensorbank/tf/points.py
tensorbank/tf/slices.py
tensorbank-0.2.1.dist-info/LICENSE
tensorbank-0.2.1.dist-info/WHEEL
tensorbank-0.2.1.dist-info/METADATA
tensorbank-0.2.1.dist-info/RECORD
