Metadata-Version: 2.1
Name: tensorbank
Version: 0.2.1
Summary: a collection of assorted algorithms expressed in Tensors.
Home-page: http://github.com/pshved/tensorbank
License: MIT
Author: Paul Shved
Author-email: pavel.shved@gmail.com
Requires-Python: >=3.6,<4.0
Classifier: License :: OSI Approved :: MIT License
Classifier: Programming Language :: Python :: 3
Classifier: Programming Language :: Python :: 3.6
Classifier: Programming Language :: Python :: 3.7
Classifier: Programming Language :: Python :: 3.8
Requires-Dist: numpy (>=1.19.0,<2.0.0)
Requires-Dist: tensorflow (>=2.0)
Project-URL: Documentation, https://tensorbank.readthedocs.io/
Project-URL: Repository, https://github.com/pshved/tensorbank
